mtc/__init__.py
mtc/mumu.py
mtc_mumu-0.0.2.dist-info/METADATA
mtc_mumu-0.0.2.dist-info/WHEEL
mtc_mumu-0.0.2.dist-info/top_level.txt
mtc_mumu-0.0.2.dist-info/RECORD
