Metadata-Version: 2.1
Name: mtc-mumu
Version: 0.0.2
Summary: 触控-mumu
Author: KateTsengK
Author-email: cu2171505467@gmail.com
License: MIT
Keywords: Auto Script Testing
Requires-Python: >=3
Requires-Dist: mtc-base
Requires-Dist: mmumu
